eindhoven/__init__.py
eindhoven/eindhoven.py
eindhoven/exceptions.py
eindhoven/models.py
eindhoven/py.typed
eindhoven-5.1.0.dist-info/LICENSE
eindhoven-5.1.0.dist-info/METADATA
eindhoven-5.1.0.dist-info/WHEEL
eindhoven-5.1.0.dist-info/RECORD
